mellon/__init__.py
mellon/adapters.py
mellon/app_settings.py
mellon/backends.py
mellon/middleware.py
mellon/models.py
mellon/models_utils.py
mellon/urls.py
mellon/utils.py
mellon/views.py
mellon/locale/fr/LC_MESSAGES/django.mo
mellon/locale/fr/LC_MESSAGES/django.po
mellon/migrations/0001_initial.py
mellon/migrations/0002_sessionindex.py
mellon/migrations/0003_add_issuer_model.py
mellon/migrations/0004_migrate_issuer.py
mellon/migrations/0005_drop_rename_issuer.py
mellon/migrations/0006_nameid_attributes.py
mellon/migrations/0007_sessionindex_transient_name_id.py
mellon/migrations/0008_add_timestamp_to_session_index.py
mellon/migrations/__init__.py
mellon/sessions_backends/__init__.py
mellon/sessions_backends/cached_db.py
mellon/sessions_backends/db.py
mellon/templates/mellon/authentication_failed.html
mellon/templates/mellon/base.html
mellon/templates/mellon/debug_login.html
mellon/templates/mellon/inactive_user.html
mellon/templates/mellon/metadata.xml
mellon/templates/mellon/session_dump.xml
mellon/templates/mellon/user_not_found.html
django_mellon-1.55.dist-info/COPYING
django_mellon-1.55.dist-info/METADATA
django_mellon-1.55.dist-info/WHEEL
django_mellon-1.55.dist-info/top_level.txt
django_mellon-1.55.dist-info/RECORD
