Metadata-Version: 2.1
Name: django-mellon
Version: 1.55
Summary: SAML 2.0 authentication for Django
Home-page: http://dev.entrouvert.org/projects/django-mellon/
Author: Entr'ouvert
Author-email: info@entrouvert.org
License: AGPLv3 or later
License-File: COPYING
Requires-Dist: atomicwrites
Requires-Dist: django <4.3,>=3.2
Requires-Dist: isodate
Requires-Dist: requests
